<?xml version="1.0" encoding="UTF-8" standalone="yes"?>
<LabCollection>
    <LabWork>
        <averagePoint>43</averagePoint>
        <coordinates>
            <x>34</x>
            <y>3</y>
        </coordinates>
        <creationDate>2021-04-02T23:37:59.835+03:00[Europe/Moscow]</creationDate>
        <difficulty>TERRIBLE</difficulty>
        <discipline>
            <labsCount>43</labsCount>
            <name>sdf</name>
        </discipline>
        <id>2</id>
        <minimalPoint>34</minimalPoint>
        <name>anna</name>
        <tunedInWorks>34</tunedInWorks>
    </LabWork>
    <LabWork>
        <averagePoint>7</averagePoint>
        <coordinates>
            <x>23</x>
            <y>23</y>
        </coordinates>
        <creationDate>2021-04-02T23:37:59.851+03:00[Europe/Moscow]</creationDate>
        <difficulty>HARD</difficulty>
        <discipline>
            <labsCount>23</labsCount>
            <name>sdf</name>
        </discipline>
        <id>5</id>
        <minimalPoint>32</minimalPoint>
        <name>egor</name>
        <tunedInWorks>5</tunedInWorks>
    </LabWork>
    <LabWork>
        <averagePoint>23</averagePoint>
        <coordinates>
            <x>43</x>
            <y>4</y>
        </coordinates>
        <creationDate>2021-04-02T23:37:59.851+03:00[Europe/Moscow]</creationDate>
        <difficulty>HARD</difficulty>
        <discipline>
            <labsCount>234</labsCount>
            <name>sdf</name>
        </discipline>
        <id>1</id>
        <minimalPoint>65</minimalPoint>
        <name>elena</name>
        <tunedInWorks>34</tunedInWorks>
    </LabWork>
    <LabWork>
        <averagePoint>2</averagePoint>
        <coordinates>
            <x>34</x>
            <y>34</y>
        </coordinates>
        <creationDate>2021-04-02T23:37:59.851+03:00[Europe/Moscow]</creationDate>
        <difficulty>HARD</difficulty>
        <discipline>
            <labsCount>3</labsCount>
            <name>sdf</name>
        </discipline>
        <id>4</id>
        <minimalPoint>34</minimalPoint>
        <name>georgy</name>
        <tunedInWorks>3</tunedInWorks>
    </LabWork>
    <LabWork>
        <averagePoint>54</averagePoint>
        <coordinates>
            <x>34</x>
            <y>34</y>
        </coordinates>
        <creationDate>2021-04-02T23:37:59.851+03:00[Europe/Moscow]</creationDate>
        <difficulty>HARD</difficulty>
        <discipline>
            <labsCount>32</labsCount>
            <name>sdf</name>
        </discipline>
        <id>3</id>
        <minimalPoint>3</minimalPoint>
        <name>максим</name>
        <tunedInWorks>545</tunedInWorks>
    </LabWork>
</LabCollection>
